{"cameraMode":{"drawMode":0,"name":"Shaded","section":"Shading Mode"},"sceneLighting":true,"audioPlay":false,"sceneViewState":{"m_AlwaysRefresh":false,"showFog":true,"showSkybox":true,"showFlares":true,"showImageEffects":true,"showParticleSystems":true,"showVisualEffectGraphs":true,"m_FxEnabled":true},"in2DMode":false,"pivot":{"x":-425.2891845703125,"y":4.962318420410156,"z":-106.22245025634766},"rotation":{"x":-0.0022654240019619467,"y":0.9848303198814392,"z":-0.17341873049736024,"w":-0.012364091351628304},"size":2.4685258865356447,"orthographic":false}